{
  "students": [
    {
      "name": "ff",
      "lastname": "ff",
      "mark": "77",
      "marked_date": "18:55:26",
      "id": 1
    },
    {
      "name": "ыфв",
      "lastname": "32",
      "mark": "22",
      "marked_date": "18:55:41",
      "id": 3
    },
    {
      "name": "a",
      "lastname": "b",
      "mark": "77",
      "marked_date": "16:44:42",
      "id": 4
    },
    {
      "name": "aaaaaaa",
      "lastname": "tttttt",
      "mark": "11",
      "marked_date": "16:43:15",
      "id": 5
    },
    {
      "name": "aaa",
      "lastname": "dddd",
      "mark": "32",
      "marked_date": "18:55:16",
      "id": 6
    }
  ]
}